[
    {
        "agentType": "prometheus",
        "help": "Whether the MySQL server is up.",
        "key": "mysql_up",
        "data_type": "double",
        "metric_type": "gauge",
        "paramDefine": [],
        "tagDefine": [],
        "unit": ""
    },
    {
        "agentType": "prometheus",
        "help": "Generic metric from SHOW GLOBAL STATUS.",
        "key": "mysql_global_status_aborted_connects",
        "data_type": "double",
        "metric_type": "gauge",
        "paramDefine": [],
        "tagDefine": [],
        "unit": ""
    },
    {
        "agentType": "prometheus",
        "help": "Generic metric from SHOW GLOBAL STATUS.",
        "key": "mysql_global_status_aborted_connects",
        "data_type": "double",
        "metric_type": "gauge",
        "paramDefine": [],
        "tagDefine": [],
        "unit": ""
    },
    {
        "agentType": "prometheus",
        "help": "Generic metric from SHOW GLOBAL STATUS.",
        "key": "mysql_global_status_max_used_connections",
        "data_type": "double",
        "metric_type": "gauge",
        "paramDefine": [],
        "tagDefine": [],
        "unit": ""
    },
    {
        "agentType": "prometheus",
        "help": "Generic gauge metric from SHOW GLOBAL VARIABLES.",
        "key": "mysql_global_variables_max_connections",
        "data_type": "double",
        "metric_type": "gauge",
        "paramDefine": [],
        "tagDefine": [],
        "unit": ""
    },
    {
        "agentType": "prometheus",
        "help": "Generic gauge metric from SHOW GLOBAL VARIABLES.",
        "key": "mysql_global_variables_long_query_time",
        "data_type": "double",
        "metric_type": "gauge",
        "paramDefine": [],
        "tagDefine": [],
        "unit": ""
    },
    {
        "agentType": "prometheus",
        "help": "Generic metric from SHOW GLOBAL STATUS.",
        "key": "mysql_global_status_slow_queries",
        "data_type": "double",
        "metric_type": "gauge",
        "paramDefine": [],
        "tagDefine": [],
        "unit": ""
    },
    {
        "agentType": "prometheus",
        "help": "Generic metric from SHOW SLAVE STATUS.",
        "key": "mysql_slave_status_slave_io_running",
        "paramDefine": [
            {
                "name": "channel_name",
                "readOnly": false,
                "valueType": "string"
            },
            {
                "name": "connection_name",
                "readOnly": false,
                "valueType": "string"
            },
            {
                "name": "master_host",
                "readOnly": false,
                "valueType": "string"
            },
            {
                "name": "master_uuid",
                "readOnly": false,
                "valueType": "string"
            }
        ],
        "tagDefine": [
            {
                "name": "channel_name",
                "readOnly": false
            },
            {
                "name": "connection_name",
                "readOnly": false
            },
            {
                "name": "master_host",
                "readOnly": false
            },
            {
                "name": "master_uuid",
                "readOnly": false
            }
        ],
        "data_type": "double",
        "metric_type": "gauge",
        "unit": ""
    },
    {
        "agentType": "prometheus",
        "help": "Generic metric from SHOW SLAVE STATUS.",
        "key": "mysql_slave_status_slave_sql_running",
        "paramDefine": [
            {
                "name": "channel_name",
                "readOnly": false,
                "valueType": "string"
            },
            {
                "name": "connection_name",
                "readOnly": false,
                "valueType": "string"
            },
            {
                "name": "master_host",
                "readOnly": false,
                "valueType": "string"
            },
            {
                "name": "master_uuid",
                "readOnly": false,
                "valueType": "string"
            }
        ],
        "tagDefine": [
            {
                "name": "channel_name",
                "readOnly": false
            },
            {
                "name": "connection_name",
                "readOnly": false
            },
            {
                "name": "master_host",
                "readOnly": false
            },
            {
                "name": "master_uuid",
                "readOnly": false
            }
        ],
        "data_type": "double",
        "metric_type": "gauge",
        "unit": ""
    },
    {
        "agentType": "prometheus",
        "help": "Generic metric from SHOW SLAVE STATUS.",
        "key": "mysql_slave_status_seconds_behind_master",
        "paramDefine": [
            {
                "name": "channel_name",
                "readOnly": false,
                "valueType": "string"
            },
            {
                "name": "connection_name",
                "readOnly": false,
                "valueType": "string"
            },
            {
                "name": "master_host",
                "readOnly": false,
                "valueType": "string"
            },
            {
                "name": "master_uuid",
                "readOnly": false,
                "valueType": "string"
            }
        ],
        "tagDefine": [
            {
                "name": "channel_name",
                "readOnly": false
            },
            {
                "name": "connection_name",
                "readOnly": false
            },
            {
                "name": "master_host",
                "readOnly": false
            },
            {
                "name": "master_uuid",
                "readOnly": false
            }
        ],
        "unit": "seconds",
        "data_type": "double",
        "metric_type": "gauge"
    },
    {
        "agentType": "prometheus",
        "help": "Generic metric from SHOW GLOBAL STATUS.",
        "key": "mysql_global_status_uptime",
        "data_type": "double",
        "metric_type": "gauge",
        "paramDefine": [],
        "tagDefine": [],
        "unit": ""
    },
    {
        "tagDefine": [],
        "help": "Generic metric from SHOW GLOBAL STATUS.",
        "data_type": "double",
        "paramDefine": [],
        "agentType": "prometheus",
        "key": "mysql_global_status_bytes_sent",
        "metric_type": "counter",
        "unit": "bytes"
    },
    {
        "tagDefine": [],
        "help": "Generic metric from SHOW GLOBAL STATUS.",
        "data_type": "double",
        "paramDefine": [],
        "agentType": "calculated",
        "key": "mysql_global_status_bytes_sent_rate",
        "metric_type": "gauge",
        "expression": "rate(mysql_global_status_bytes_sent[1m])",
        "unit": "bytes/min"
    },
    {
        "tagDefine": [],
        "help": "Generic metric from SHOW GLOBAL STATUS.",
        "data_type": "double",
        "paramDefine": [],
        "agentType": "prometheus",
        "key": "mysql_global_status_qcache_free_memory",
        "metric_type": "gauge",
        "unit": ""
    },
    {
        "tagDefine": [],
        "help": "Generic metric from SHOW GLOBAL STATUS.",
        "data_type": "double",
        "paramDefine": [],
        "agentType": "prometheus",
        "key": "mysql_global_status_queries",
        "metric_type": "counter",
        "unit": ""
    },
    {
        "tagDefine": [],
        "help": "Generic metric from SHOW GLOBAL STATUS.",
        "data_type": "double",
        "paramDefine": [],
        "agentType": "calculated",
        "key": "mysql_global_status_queries_rate",
        "metric_type": "gauge",
        "expression": "rate(mysql_global_status_queries[1m])",
        "unit": ""
    },
    {
        "tagDefine": [],
        "help": "Generic gauge metric from SHOW GLOBAL VARIABLES.",
        "data_type": "double",
        "paramDefine": [],
        "agentType": "prometheus",
        "key": "mysql_global_variables_max_connections",
        "metric_type": "gauge",
        "unit": ""
    },
    {
        "tagDefine": [],
        "help": "Generic metric from SHOW GLOBAL STATUS.",
        "data_type": "double",
        "paramDefine": [],
        "agentType": "prometheus",
        "key": "mysql_global_status_uptime",
        "metric_type": "counter",
        "unit": ""
    },
    {
        "tagDefine": [],
        "help": "Generic metric from SHOW GLOBAL STATUS.",
        "data_type": "double",
        "paramDefine": [],
        "agentType": "prometheus",
        "key": "mysql_global_status_innodb_num_open_files",
        "metric_type": "gauge",
        "unit": ""
    },
    {
        "tagDefine": [],
        "help": "Generic gauge metric from SHOW GLOBAL VARIABLES.",
        "data_type": "double",
        "paramDefine": [],
        "agentType": "prometheus",
        "key": "mysql_global_variables_thread_cache_size",
        "metric_type": "gauge",
        "unit": ""
    },
    {
        "tagDefine": [],
        "help": "Generic gauge metric from SHOW GLOBAL VARIABLES.",
        "data_type": "double",
        "paramDefine": [],
        "agentType": "prometheus",
        "key": "mysql_global_variables_query_cache_size",
        "metric_type": "gauge",
        "unit": ""
    },
    {
        "tagDefine": [],
        "help": "Generic metric from SHOW GLOBAL STATUS.",
        "data_type": "double",
        "paramDefine": [],
        "agentType": "prometheus",
        "key": "mysql_global_status_max_used_connections",
        "metric_type": "gauge",
        "unit": ""
    },
    {
        "tagDefine": [],
        "help": "Generic metric from SHOW GLOBAL STATUS.",
        "data_type": "double",
        "paramDefine": [],
        "agentType": "prometheus",
        "key": "mysql_global_status_threads_created",
        "metric_type": "gauge",
        "unit": ""
    },
    {
        "tagDefine": [],
        "help": "Generic metric from SHOW GLOBAL STATUS.",
        "data_type": "double",
        "paramDefine": [],
        "agentType": "calculated",
        "key": "mysql_global_status_threads_created_rate",
        "metric_type": "gauge",
        "expression": "rate(mysql_global_status_threads_created[1m])",
        "unit": ""
    },
    {
        "tagDefine": [],
        "help": "Generic metric from SHOW GLOBAL STATUS.",
        "data_type": "double",
        "paramDefine": [],
        "agentType": "prometheus",
        "key": "mysql_global_status_threads_cached",
        "metric_type": "gauge",
        "unit": ""
    },
    {
        "tagDefine": [],
        "help": "Generic metric from SHOW GLOBAL STATUS.",
        "data_type": "double",
        "paramDefine": [],
        "agentType": "prometheus",
        "key": "mysql_global_status_questions",
        "metric_type": "counter",
        "unit": ""
    },
    {
        "tagDefine": [],
        "help": "Generic metric from SHOW GLOBAL STATUS.",
        "data_type": "double",
        "paramDefine": [],
        "agentType": "calculated",
        "key": "mysql_global_status_questions_rate",
        "metric_type": "gauge",
        "expression": "rate(mysql_global_status_questions[1m])",
        "unit": ""
    },
    {
        "tagDefine": [],
        "help": "Generic metric from SHOW GLOBAL STATUS.",
        "data_type": "double",
        "paramDefine": [],
        "agentType": "prometheus",
        "key": "mysql_global_status_threads_connected",
        "metric_type": "gauge",
        "unit": ""
    },
    {
        "tagDefine": [],
        "help": "Generic metric from SHOW GLOBAL STATUS.",
        "data_type": "double",
        "paramDefine": [],
        "agentType": "calculated",
        "key": "mysql_global_status_threads_connected_max",
        "metric_type": "gauge",
        "expression": "max_over_time(mysql_global_status_threads_connected[1m])",
        "unit": ""
    },
    {
        "tagDefine": [],
        "help": "Generic metric from SHOW GLOBAL STATUS.",
        "data_type": "double",
        "paramDefine": [],
        "agentType": "prometheus",
        "key": "mysql_global_status_opened_files",
        "metric_type": "gauge",
        "unit": ""
    },
    {
        "tagDefine": [],
        "help": "Generic metric from SHOW GLOBAL STATUS.",
        "data_type": "double",
        "paramDefine": [],
        "agentType": "calculated",
        "key": "mysql_global_status_opened_files_rate",
        "metric_type": "gauge",
        "expression": "rate(mysql_global_status_opened_files[1m])",
        "unit": ""
    },
    {
        "tagDefine": [],
        "help": "Generic metric from SHOW GLOBAL STATUS.",
        "data_type": "double",
        "paramDefine": [],
        "agentType": "prometheus",
        "key": "mysql_global_status_bytes_received",
        "metric_type": "counter",
        "unit": "bytes"
    },
    {
        "tagDefine": [],
        "help": "Generic metric from SHOW GLOBAL STATUS.",
        "data_type": "double",
        "paramDefine": [],
        "agentType": "calculated",
        "key": "mysql_global_status_bytes_received_rate",
        "metric_type": "gauge",
        "expression": "rate(mysql_global_status_bytes_received[1m])",
        "unit": "bytes/min"
    },
    {
        "tagDefine": [],
        "help": "Generic gauge metric from SHOW GLOBAL VARIABLES.",
        "data_type": "double",
        "paramDefine": [],
        "agentType": "prometheus",
        "key": "mysql_global_variables_innodb_buffer_pool_size",
        "metric_type": "gauge",
        "unit": ""
    },
    {
        "tagDefine": [],
        "help": "Generic gauge metric from SHOW GLOBAL VARIABLES.",
        "data_type": "double",
        "paramDefine": [],
        "agentType": "prometheus",
        "key": "mysql_global_variables_open_files_limit",
        "metric_type": "gauge",
        "unit": ""
    },
    {
        "tagDefine": [],
        "help": "Generic metric from SHOW GLOBAL STATUS.",
        "data_type": "double",
        "paramDefine": [],
        "agentType": "prometheus",
        "key": "mysql_global_status_open_files",
        "metric_type": "gauge",
        "unit": ""
    },
    {
        "tagDefine": [],
        "help": "Generic metric from SHOW GLOBAL STATUS.",
        "data_type": "double",
        "paramDefine": [],
        "agentType": "prometheus",
        "key": "mysql_global_status_threads_running",
        "metric_type": "gauge",
        "unit": ""
    },
    {
        "tagDefine": [],
        "help": "Generic metric from SHOW GLOBAL STATUS.",
        "data_type": "double",
        "paramDefine": [],
        "agentType": "calculated",
        "key": "mysql_global_status_threads_running_max",
        "metric_type": "gauge",
        "expression": "max_over_time(mysql_global_status_threads_running[1m])",
        "unit": ""
    },
    {
        "tagDefine": [],
        "help": "Generic metric from SHOW GLOBAL STATUS.",
        "data_type": "double",
        "paramDefine": [],
        "agentType": "calculated",
        "key": "mysql_global_status_threads_running_avg",
        "metric_type": "gauge",
        "expression": "avg_over_time(mysql_global_status_threads_running[1m])",
        "unit": ""
    }
]
